{
  "Version": "0.1",
  "Active": true,
  "Base_Path": "img/minigame/masculinity/cocks/",
  "Dick_Type_Map": [
    {
      "Dick_Type": "bwc",
      "Rating_Map": [
        [
          1,
          "tight",
          "long",
          "smooth",
          7,
          7,
          10,
          5
        ],
        [
          13,
          "smooth",
          "veiny",
          "uncircumcised",
          7,
          7,
          8,
          6
        ],
        [
          22,
          "hairy",
          "veiny",
          "mushroom-shaped",
          7,
          8,
          7,
          7
        ],
        [
          23,
          "bloated",
          "smooth",
          "triangular",
          7,
          7,
          8,
          6
        ],
        [
          29,
          "dangling",
          "uncut",
          "uncircumcised",
          7,
          8,
          8,
          8
        ],
        [
          32,
          "hairy",
          "fat",
          "thick",
          7,
          10,
          7,
          7
        ],
        [
          37,
          "hairy",
          "veiny",
          "dark purple",
          7,
          6,
          6,
          6
        ],
        [
          41,
          "full-looking",
          "veiny",
          "stubby",
          7,
          6,
          7,
          10
        ],
        [
          46,
          "dangling",
          "veiny",
          "slender",
          7,
          5,
          8,
          5
        ],
        [
          48,
          "big, smooth",
          "smooth",
          "dome-shaped",
          7,
          8,
          8,
          6
        ],
        [
          49,
          "giant",
          "fat",
          "triangular",
          7,
          9,
          9,
          9
        ],
        [
          54,
          "wrinkly",
          "curved",
          "sculpted",
          7,
          7,
          7,
          7
        ],
        [
          79,
          "heavy",
          "thick",
          "hefty",
          7,
          9,
          10,
          10
        ],
        [
          87,
          "dangling",
          "veiny",
          "shiny, flared",
          7,
          6,
          6,
          8
        ],
        [
          92,
          "hefty",
          "stubby",
          "red, precum-drooling",
          7,
          5,
          5,
          5
        ],
        [
          93,
          "smooth",
          "thick",
          "helmet-shaped",
          7,
          6,
          8,
          8
        ],
        [
          96,
          "dangling",
          "veiny",
          "red, mushroom-shaped",
          7,
          6,
          5,
          8
        ],
        [
          97,
          "huge",
          "smooth",
          "smooth, mushroom-shaped",
          7,
          7,
          7,
          4
        ],
        [
          99,
          "hairy",
          "long",
          "red, sculpted",
          7,
          7,
          10,
          5
        ],
        [
          113,
          "red",
          "red",
          "red, oval-shaped",
          7,
          6,
          6,
          4
        ],
        [
          137,
          "hairy",
          "dark-colored",
          "dome-shaped",
          7,
          5,
          5,
          6
        ],
        [
          147,
          "smooth",
          "slender",
          "elegant",
          7,
          5,
          9,
          9
        ],
        [
          149,
          "dangling",
          "curved",
          "helmet-shaped",
          7,
          7,
          7,
          10
        ],
        [
          161,
          "fat",
          "veiny",
          "mushroom-shaped",
          7,
          6,
          7,
          10
        ],
        [
          165,
          "smooth",
          "veiny",
          "pink",
          7,
          8,
          7,
          6
        ],
        [
          176,
          "bloated",
          "bulbous",
          "triangular",
          7,
          5,
          7,
          10
        ],
        [
          177,
          "super-hairy",
          "thickly-veined",
          "helmet-shaped",
          7,
          4,
          8,
          6
        ],
        [
          184,
          "hairy",
          "smooth",
          "red",
          7,
          7,
          7,
          7
        ],
        [
          190,
          "tight",
          "slender",
          "pointy",
          7,
          2,
          10,
          9
        ],
        [
          191,
          "dangly",
          "red",
          "helmet-shaped",
          7,
          6,
          7,
          9
        ],
        {
          "Rate": 7,
          "Dick_List": [
            {
              "Picture_Name": "",
              "Img_Type": ".jpg",
              "Balls_Desc": "",
              "Cock_Desc": "",
              "Tip_Desc": "",
              "Cock_Fatness": 0,
              "Cock_Length": 0,
              "Ball_Size": 0
            }
          ]
        },
        [
          7,
          "big",
          "veiny",
          "round",
          8,
          8,
          10,
          8
        ],
        [
          8,
          "full-looking",
          "veiny",
          "bulbous",
          8,
          7,
          10,
          7
        ],
        [
          11,
          "big",
          "veiny",
          "sculpted",
          8,
          7,
          10,
          7
        ],
        [
          15,
          "smooth",
          "curved",
          "sculptural",
          8,
          8,
          9,
          6
        ],
        [
          17,
          "shaved",
          "veiny",
          "flared",
          8,
          6,
          8,
          6
        ],
        [
          18,
          "shaved",
          "veiny",
          "pink",
          8,
          9,
          10,
          6
        ],
        [
          21,
          "dangling",
          "veiny",
          "helmet-shaped",
          8,
          7,
          7,
          8
        ],
        [
          28,
          "smooth",
          "smooth",
          "smooth, red",
          8,
          6,
          7,
          5
        ],
        [
          44,
          "hairy, wrinkly",
          "veiny",
          "purple",
          8,
          10,
          8,
          9
        ],
        [
          50,
          "big, smooth",
          "curved",
          "shiny",
          8,
          7,
          9,
          7
        ],
        [
          60,
          "lopsided",
          "pale",
          "shiny, red",
          8,
          7,
          8,
          7
        ],
        [
          66,
          "hairy",
          "veiny",
          "triangular",
          8,
          6,
          8,
          8
        ],
        [
          67,
          "hairy",
          "veiny",
          "fat",
          8,
          9,
          7,
          7
        ],
        [
          74,
          "tight",
          "veiny",
          "helmet-shaped",
          8,
          10,
          8,
          4
        ],
        [
          80,
          "smooth",
          "uncut",
          "red, uncircumcised",
          8,
          7,
          7,
          8
        ],
        [
          84,
          "heavy",
          "fat",
          "angular",
          8,
          9,
          10,
          5
        ],
        [
          85,
          "heavy",
          "meaty",
          "domed",
          8,
          6,
          5,
          7
        ],
        [
          94,
          "heavy",
          "uncut",
          "uncircumcised",
          8,
          6,
          6,
          6
        ],
        [
          95,
          "tight",
          "veiny",
          "precum-drooling",
          8,
          7,
          6,
          3
        ],
        [
          103,
          "dangling",
          "veiny",
          "helmet-shaped",
          8,
          5,
          6,
          10
        ],
        [
          104,
          "red",
          "veiny",
          "wide-brimmed",
          8,
          6,
          7,
          6
        ],
        [
          126,
          "hefty",
          "uncut",
          "uncircumcised",
          8,
          7,
          5,
          6
        ],
        [
          141,
          "hairy",
          "fat",
          "helmet-shaped",
          8,
          10,
          6,
          9
        ],
        [
          142,
          "smooth",
          "extremely veiny",
          "red",
          8,
          9,
          7,
          10
        ],
        [
          144,
          "hairy",
          "banana-shaped",
          "shiny",
          8,
          10,
          7,
          10
        ],
        [
          150,
          "hairy",
          "aggressive-looking",
          "shiny",
          8,
          9,
          8,
          7
        ],
        [
          151,
          "wrinkly",
          "curved",
          "red",
          8,
          8,
          9,
          7
        ],
        [
          153,
          "smooth",
          "elegant",
          "uncut",
          8,
          8,
          7,
          9
        ],
        [
          154,
          "wrinkly",
          "heavily-veined",
          "uncut",
          8,
          8,
          7,
          7
        ],
        [
          157,
          "hairless",
          "smooth",
          "mushroom-shaped",
          8,
          8,
          8,
          9
        ],
        [
          158,
          "dark-colored",
          "curved",
          "mushroom-shaped",
          8,
          8,
          9,
          6
        ],
        [
          166,
          "wrinkly",
          "veiny",
          "mushroom-shaped",
          8,
          8,
          9,
          8
        ],
        [
          169,
          "dark-colored",
          "purple",
          "shiny",
          8,
          8,
          8,
          9
        ],
        [
          173,
          "tight",
          "long",
          "uncut",
          8,
          6,
          10,
          8
        ],
        [
          183,
          "dangling",
          "equine",
          "uncut",
          8,
          7,
          9,
          10
        ],
        [
          189,
          "imposing",
          "veiny",
          "red",
          8,
          8,
          7,
          10
        ],
        [
          192,
          "wrinkly",
          "curved",
          "helmet-shaped",
          8,
          7,
          8,
          5
        ],
        {
          "Rate": 8,
          "Dick_List": [
            {
              "Picture_Name": "",
              "Img_Type": ".jpg",
              "Balls_Desc": "",
              "Cock_Desc": "",
              "Tip_Desc": "",
              "Cock_Fatness": 0,
              "Cock_Length": 0,
              "Ball_Size": 0
            }
          ]
        }
      ]
    }
  ]
}